bvhTools/__init__.py
bvhTools/angleConversion.py
bvhTools/bvhDataTypes.py
bvhTools/bvhIO.py
bvhTools/bvhManipulation.py
bvhTools/bvhMetrics.py
bvhTools/bvhSkeletonEditor.py
bvhTools/bvhSlicer.py
bvhTools/bvhToolsCli.py
bvhTools/bvhVisualizerMpl.py
bvhtools-1.4.4.dist-info/METADATA
bvhtools-1.4.4.dist-info/WHEEL
bvhtools-1.4.4.dist-info/entry_points.txt
bvhtools-1.4.4.dist-info/licenses/LICENSE
bvhtools-1.4.4.dist-info/RECORD
