Metadata-Version: 2.4
Name: bvhTools
Version: 1.4.4
Summary: Easy to use package to work with BVH (BioVision Hierarchy) files.
Project-URL: Homepage, https://github.com/Enekoassets/bvhTools
Project-URL: Issues, https://github.com/Enekoassets/bvhTools/issues
Project-URL: Documentation, https://enekoassets.github.io/bvhTools/
Author-email: Eneko Assets <enekoassets@gmail.com>
License-Expression: MIT
License-File: LICENSE
Classifier: Operating System :: OS Independent
Classifier: Programming Language :: Python :: 3
Requires-Python: >=3.9
Requires-Dist: matplotlib>=3.9.0
Requires-Dist: numpy>=1.26.4
Requires-Dist: pillow>=10.1.0
Requires-Dist: scipy>=1.13.1
